main.py
friendly_package-1.1.dist-info/LICENSE
friendly_package-1.1.dist-info/METADATA
friendly_package-1.1.dist-info/WHEEL
friendly_package-1.1.dist-info/top_level.txt
friendly_package-1.1.dist-info/RECORD
