Metadata-Version: 2.1
Name: friendly-package
Version: 1.1
Summary: this package does nothing, its purpose lies solely in ensuring pypis upload policy
Home-page: UNKNOWN
Author: leo
Author-email: l.ricker93@web.de
License: GPLv2
Platform: UNKNOWN
